{
  "mapping": {
    "dependsOn": [
      "007-single-container-packaging",
      "008-vendored-encore-toolchain"
    ],
    "implementingPaths": [
      {
        "path": ".github/workflows/image.yml",
        "source": "spec-edge"
      }
    ],
    "resolvedUnits": [
      {
        "locations": [
          {
            "file": ".github/workflows/image.yml"
          }
        ],
        "ownership": true,
        "sourceField": "establishes",
        "unit": {
          "kind": "file",
          "path": ".github/workflows/image.yml"
        }
      }
    ],
    "specId": "016-amd64-image",
    "specStatus": "approved"
  },
  "schemaVersion": "1.1.0",
  "shardHash": "b024ecfdb0e169622c60ad4155627bb16f92cb36e50682071d4fb94f779f7ba2"
}
